package_viacep/__init__.py
package_viacep/viacep.py
package_viacep-0.0.1.dist-info/METADATA
package_viacep-0.0.1.dist-info/WHEEL
package_viacep-0.0.1.dist-info/top_level.txt
package_viacep-0.0.1.dist-info/RECORD
