Metadata-Version: 2.1
Name: package-viacep
Version: 0.0.1
Summary: Utility for Brazil zip code query or validation
Home-page: https://github.com/antonioliverjr/package_viacep
Author: Antonio Oliveira
Author-email: antoniobatistajr@gmail.com
License: UNKNOWN
Platform: UNKNOWN
Requires-Python: >=3.8
Requires-Dist: requests (==2.27.1)
Requires-Dist: requests-toolbelt (==0.9.1)
